clubhouse_client/__init__.py
clubhouse_client/client.py
clubhouse_client/resources/__init__.py
clubhouse_client/resources/common.py
clubhouse_client/resources/stories.py
clubhouse_client-0.1.3.dist-info/LICENSE
clubhouse_client-0.1.3.dist-info/WHEEL
clubhouse_client-0.1.3.dist-info/METADATA
clubhouse_client-0.1.3.dist-info/RECORD
